envision/__init__.py
envision/envision.py
envision/tests/__init__.py
envision/tests/dev_warnings/.envision
envision/tests/git_warnings/.envision
envision/tests/git_warnings/.gitignore
envision/tests/invalid_envision_file/.envision
envision/tests/invalid_envision_key_value/.envision
envision/tests/invalid_envision_lock_file/.envision.lock
envision/tests/invalid_envision_lock_key_value/.envision.lock
envision/tests/prod_warnings/.envision.key
envision/tests/prod_warnings/.envision.lock
envision/tests/test_envision.py
envision/tests/valid_dev/.envision
envision/tests/valid_prod/.envision.lock
envision-0.1.1.dist-info/entry_points.txt
envision-0.1.1.dist-info/WHEEL
envision-0.1.1.dist-info/METADATA
envision-0.1.1.dist-info/RECORD
